vers/__init__.py
vers/vers.py
vers-1.0.2.dist-info/METADATA
vers-1.0.2.dist-info/RECORD
vers-1.0.2.dist-info/WHEEL
vers-1.0.2.dist-info/top_level.txt
