Metadata-Version: 2.1
Name: vers
Version: 1.0.2
Summary: Version Comparision
Home-page: https://github.com/amirmd76/vers
Author: AmirMohammad Dehghan
Author-email: amirmd76@gmail.com
License: MIT
Platform: UNKNOWN
Classifier: License :: OSI Approved :: MIT License
Classifier: Topic :: Utilities
Classifier: Programming Language :: Python
